tidytextpy/__init__.py
tidytextpy/tidytextpy.py
tidytextpy/dictionary/afinn.csv
tidytextpy/dictionary/bing.csv
tidytextpy/dictionary/chinese.txt
tidytextpy/dictionary/dutir.csv
tidytextpy/dictionary/english.txt
tidytextpy/dictionary/hownet.csv
tidytextpy/dictionary/nrc.csv
tidytextpy-1.0.dist-info/LICENSE
tidytextpy-1.0.dist-info/METADATA
tidytextpy-1.0.dist-info/WHEEL
tidytextpy-1.0.dist-info/top_level.txt
tidytextpy-1.0.dist-info/RECORD
