Metadata-Version: 2.1
Name: tidytextpy
Version: 1.0
Summary: 将R语言tidytext包移植到Python，可简单调用unnest_tokens、get_sentiments、get_stopwords、bind_tf_idf等函数。
Home-page: https://github.com/hidadeng/tidytextpy
Author: 大邓
Author-email: thunderhit@qq.com
License: MIT
Keywords: tidytext,text analysis,sentiment,sentiment analysis,natural language processing,R,python
Platform: UNKNOWN
Requires-Python: >=3.5
